[
  {
    "uniqueIdentifier": "728aee3c-1bf9-48b3-83a8-6630d806b80e",
    "payload": {
      "name": "EventStream",
      "metadata": {
        "eventstreamArtifactId": "4bda8cbd-96c8-4777-b42a-5a073a76d849"
      }
    },
    "type": "eventstreamSource-v1"
  },
  {
    "uniqueIdentifier": "912c1646-384f-4ca0-beaa-1e615310b713",
    "payload": {
      "name": "new_eventstream-stream",
      "definition": {
        "type": "Event",
        "instance": "{\"templateId\":\"SourceEvent\",\"templateVersion\":\"1.1\",\"steps\":[{\"name\":\"SourceEventStep\",\"id\":\"40d15f46-39a4-4e94-9840-b50ee070a5ea\",\"rows\":[{\"name\":\"SourceSelector\",\"kind\":\"SourceReference\",\"arguments\":[{\"name\":\"entityId\",\"type\":\"string\",\"value\":\"728aee3c-1bf9-48b3-83a8-6630d806b80e\"}]}]}]}"
      }
    },
    "type": "timeSeriesView-v1"
  },
  {
    "uniqueIdentifier": "fab686d3-fb2c-48a5-8c31-a024e2963284",
    "payload": {
      "name": "symbol",
      "definition": {
        "type": "Object"
      }
    },
    "type": "timeSeriesView-v1"
  },
  {
    "uniqueIdentifier": "7cb6db73-b0da-42fe-84a7-ea0721591c45",
    "payload": {
      "name": "symbol",
      "parentObject": {
        "targetUniqueIdentifier": "fab686d3-fb2c-48a5-8c31-a024e2963284"
      },
      "definition": {
        "type": "Attribute",
        "instance": "{\"steps\":[{\"id\":\"8e614fca-6be6-4093-86af-879081e763a9\",\"name\":\"IdPartStep\",\"rows\":[{\"arguments\":[{\"name\":\"op\",\"type\":\"string\",\"value\":\"Text\"},{\"name\":\"format\",\"type\":\"string\",\"value\":\"\"}],\"kind\":\"TypeAssertion\",\"name\":\"TypeAssertion\"}]}],\"templateId\":\"IdentityPartAttribute\",\"templateVersion\":\"1.3.0\"}"
      }
    },
    "type": "timeSeriesView-v1"
  },
  {
    "uniqueIdentifier": "5275383d-e3ac-4de4-8273-908eec3a008e",
    "payload": {
      "name": "symbol",
      "parentObject": {
        "targetUniqueIdentifier": "fab686d3-fb2c-48a5-8c31-a024e2963284"
      },
      "definition": {
        "type": "Attribute",
        "instance": "{\"steps\":[{\"id\":\"7ddabf5e-8d8d-4825-b930-a522764e8e6c\",\"name\":\"IdStructureStep\",\"rows\":[{\"arguments\":[{\"arguments\":[{\"name\":\"entityId\",\"type\":\"string\",\"value\":\"7cb6db73-b0da-42fe-84a7-ea0721591c45\"}],\"kind\":\"AttributeReference\",\"name\":\"idPart\",\"type\":\"complex\"}],\"kind\":\"IdPart\",\"name\":\"IdPart\"}]}],\"templateId\":\"IdentityTupleAttribute\",\"templateVersion\":\"1.3.0\"}"
      }
    },
    "type": "timeSeriesView-v1"
  },
  {
    "uniqueIdentifier": "67f7d7dd-a476-40a7-9dce-2ebd35acf212",
    "payload": {
      "name": "Activator event",
      "parentObject": {
        "targetUniqueIdentifier": "fab686d3-fb2c-48a5-8c31-a024e2963284"
      },
      "definition": {
        "type": "Event",
        "instance": "{\"steps\":[{\"id\":\"8395507a-8aaa-4019-afbc-5cf071d63527\",\"name\":\"SplitEventStep\",\"rows\":[{\"arguments\":[{\"arguments\":[{\"name\":\"entityId\",\"type\":\"string\",\"value\":\"912c1646-384f-4ca0-beaa-1e615310b713\"}],\"kind\":\"EventReference\",\"name\":\"event\",\"type\":\"complex\"}],\"kind\":\"Event\",\"name\":\"EventSelector\"},{\"arguments\":[{\"name\":\"fieldName\",\"type\":\"string\",\"value\":\"symbol\"},{\"arguments\":[{\"name\":\"entityId\",\"type\":\"string\",\"value\":\"7cb6db73-b0da-42fe-84a7-ea0721591c45\"}],\"kind\":\"AttributeReference\",\"name\":\"idPart\",\"type\":\"complex\"}],\"kind\":\"FieldIdMapping\",\"name\":\"FieldIdMapping\"},{\"arguments\":[{\"name\":\"isAuthoritative\",\"type\":\"boolean\",\"value\":true}],\"kind\":\"EventOptions\",\"name\":\"SplitEventOptions\"}]}],\"templateId\":\"SplitEvent\",\"templateVersion\":\"1.3.0\"}"
      }
    },
    "type": "timeSeriesView-v1"
  },
  {
    "uniqueIdentifier": "1725d4bb-d473-4df4-9634-8dc94b619f76",
    "payload": {
      "name": "bidPrice",
      "parentObject": {
        "targetUniqueIdentifier": "fab686d3-fb2c-48a5-8c31-a024e2963284"
      },
      "definition": {
        "type": "Attribute",
        "instance": "{\"steps\":[{\"id\":\"d28b9cf9-ea9e-493b-90ee-b69257b5a4d5\",\"name\":\"EventSelectStep\",\"rows\":[{\"arguments\":[{\"arguments\":[{\"name\":\"entityId\",\"type\":\"string\",\"value\":\"67f7d7dd-a476-40a7-9dce-2ebd35acf212\"}],\"kind\":\"EventReference\",\"name\":\"event\",\"type\":\"complex\"}],\"kind\":\"Event\",\"name\":\"EventSelector\"},{\"arguments\":[{\"name\":\"fieldName\",\"type\":\"string\",\"value\":\"bidPrice\"}],\"kind\":\"EventField\",\"name\":\"EventFieldSelector\"}]},{\"id\":\"03974d46-7108-4400-bb96-25ea15267eb3\",\"name\":\"EventComputeStep\",\"rows\":[{\"arguments\":[{\"name\":\"op\",\"type\":\"string\",\"value\":\"Text\"},{\"name\":\"format\",\"type\":\"string\",\"value\":\"\"}],\"kind\":\"TypeAssertion\",\"name\":\"TypeAssertion\"}]}],\"templateId\":\"BasicEventAttribute\",\"templateVersion\":\"1.3.0\"}"
      }
    },
    "type": "timeSeriesView-v1"
  },
  {
    "uniqueIdentifier": "af490049-fef8-4c65-9cdc-7f85f8a2b793",
    "payload": {
      "name": "rule1",
      "parentObject": {
        "targetUniqueIdentifier": "fab686d3-fb2c-48a5-8c31-a024e2963284"
      },
      "definition": {
        "type": "Rule",
        "instance": "{\"templateId\":\"AttributeTrigger\",\"templateVersion\":\"1.3.0\",\"steps\":[{\"name\":\"ScalarSelectStep\",\"id\":\"ea01978f-6778-416a-9894-f861fe899645\",\"rows\":[{\"name\":\"AttributeSelector\",\"kind\":\"Attribute\",\"arguments\":[{\"kind\":\"AttributeReference\",\"type\":\"complex\",\"arguments\":[{\"name\":\"entityId\",\"type\":\"string\",\"value\":\"1725d4bb-d473-4df4-9634-8dc94b619f76\"}],\"name\":\"attribute\"}]}]},{\"name\":\"ScalarDetectStep\",\"id\":\"b05563c4-9ff2-4c90-806e-6b8c0fedba29\",\"rows\":[{\"name\":\"NumberValueCondition\",\"kind\":\"NumberValueCondition\",\"arguments\":[{\"name\":\"op\",\"type\":\"string\",\"value\":\"IsGreaterThan\"},{\"name\":\"threshold\",\"type\":\"number\",\"value\":1000.0}]},{\"name\":\"OccurrenceOption\",\"kind\":\"EachTime\",\"arguments\":[]}]},{\"name\":\"ActStep\",\"id\":\"7d690390-4b04-427a-a56f-efbed7bb1614\",\"rows\":[{\"name\":\"TeamsBinding\",\"kind\":\"TeamsMessage\",\"arguments\":[{\"name\":\"messageLocale\",\"type\":\"string\",\"value\":\"en-us\"},{\"name\":\"recipients\",\"type\":\"array\",\"values\":[{\"type\":\"string\",\"value\":\"Kinjalfabric@slckz.onmicrosoft.com\"}]},{\"name\":\"headline\",\"type\":\"array\",\"values\":[{\"type\":\"string\",\"value\":\"Activator alert\"}]},{\"name\":\"optionalMessage\",\"type\":\"array\",\"values\":[{\"type\":\"string\",\"value\":\"The condition has been met\"}]},{\"name\":\"additionalInformation\",\"type\":\"array\",\"values\":[]}]}]}]}",
        "settings": {
          "shouldRun": true,
          "shouldApplyRuleOnUpdate": false
        }
      }
    },
    "type": "timeSeriesView-v1"
  }
]